mkpl.py
make_playlist-1.21.0.dist-info/licenses/LICENSE.md
make_playlist-1.21.0.dist-info/METADATA
make_playlist-1.21.0.dist-info/WHEEL
make_playlist-1.21.0.dist-info/entry_points.txt
make_playlist-1.21.0.dist-info/top_level.txt
make_playlist-1.21.0.dist-info/RECORD
