Metadata-Version: 2.4
Name: make_playlist
Version: 1.21.0
Summary: Make M3U format playlist from command line.
Author-email: Matteo Guadrini <matteo.guadrini@hotmail.it>
Maintainer-email: Matteo Guadrini <matteo.guadrini@hotmail.it>
Project-URL: homepage, https://github.com/MatteoGuadrini/mkpl
Project-URL: documentation, https://matteoguadrini.github.io/mkpl/
Project-URL: changelog, https://github.com/MatteoGuadrini/mkpl/blob/master/CHANGES.md
Keywords: playlist,multimedia,file,maker,make,m3u,m3u8,cli,command line
Classifier: Programming Language :: Python :: 3
Classifier: License :: OSI Approved :: GNU General Public License v3 (GPLv3)
Classifier: Operating System :: OS Independent
Requires-Python: >=3.12
License-File: LICENSE.md
Requires-Dist: mutagen==1.47.0
Requires-Dist: tempcache==0.0.11
Dynamic: license-file
